MANIFEST.in
README
setup.py
bin/nova-backup.sh
bin/nova-snapshot.sh
bin/tempo-api
bin/tempo-backup
bin/tempo-cron-backup
bin/tempo-cron-snapshot
bin/tempo-snapshot
tempo/__init__.py
tempo/actions.py
tempo/api.py
tempo/client.py
tempo/command.py
tempo/cronspec.py
tempo/flags.py
tempo/notifier.py
tempo/queue.py
tempo.egg-info/PKG-INFO
tempo.egg-info/SOURCES.txt
tempo.egg-info/dependency_links.txt
tempo.egg-info/top_level.txt
tempo/db/__init__.py
tempo/db/api.py
tempo/db/migration.py
tempo/db/models.py
tempo/db/migrate_repo/__init__.py
tempo/db/migrate_repo/manage.py
tempo/db/migrate_repo/migrate.cfg
tempo/db/migrate_repo/schema.py
tempo/db/migrate_repo/versions/001_add_tasks_table.py
tempo/db/migrate_repo/versions/__init__.py