Metadata-Version: 1.0
Name: tempo
Version: 0.12
Summary: Tempo Service
Home-page: http://tempo.openstack.org/
Author: OpenStack
Author-email: openstack@lists.launchpad.net
License: Apache License (2.0)
Platform: UNKNOWN
Classifier: Development Status :: 4 - Beta
Classifier: License :: OSI Approved :: Apache Software License
Classifier: Operating System :: POSIX :: Linux
Classifier: Programming Language :: Python :: 2.6
Classifier: Environment :: No Input/Output (Daemon)
